{
  "SectionName": "BuildSystem",
  "SectionType": "namespace",
  "Sections": [
    {
      "SectionName": "BuildSystem",
      "SectionType": "class-definition",
      "Sections": [
        {
          "SectionName": "Targets",
          "SectionType": "namespace",
          "Sections": [],
          "Properties": []
        },
        {
          "SectionName": "BuildTargetResolver",
          "SectionType": "class-instance",
          "Sections": [
            {
              "SectionName": "_Funcs",
              "SectionType": "namespace",
              "Sections": [],
              "Properties": []
            }
          ],
          "Properties": [
            {
              "Name": "AddResolverFunc",
              "Type": "function",
              "OriginalName": "AddResolverFunc",
              "Parameters": [
                {
                  "Name": "func",
                  "IsNullChecked": true,
                  "IsOptional": false,
                  "IsRestArgs": false,
                  "Description": "Resolver Function",
                  "Type": "Function"
                }
              ],
              "Return": {
                "Type": "void",
                "Description": ""
              },
              "Description": "Adds a Resolver Function"
            },
            {
              "Name": "Resolve",
              "Type": "function",
              "OriginalName": "Resolve",
              "Parameters": [
                {
                  "Name": "name",
                  "IsNullChecked": true,
                  "IsOptional": false,
                  "IsRestArgs": false,
                  "Description": "Name of the Build Target",
                  "Type": "string"
                }
              ],
              "Return": {
                "Type": "any",
                "Description": "The Build Target with the specified name"
              },
              "Description": "Resolves a Build Target by Name"
            }
          ],
          "Description": "Resolves Build Targets by Name"
        }
      ],
      "Properties": [
        {
          "Name": "AddTargetSource",
          "Type": "function",
          "OriginalName": "AddTargetSource",
          "Parameters": [
            {
              "Name": "dir",
              "IsNullChecked": true,
              "IsOptional": false,
              "IsRestArgs": false,
              "Description": "",
              "Type": "any"
            },
            {
              "Name": "context",
              "IsNullChecked": false,
              "IsOptional": false,
              "IsRestArgs": false,
              "Description": "",
              "Type": "any"
            }
          ],
          "Return": {
            "Type": "any",
            "Description": ""
          },
          "Description": ""
        },
        {
          "Name": "Run",
          "Type": "function",
          "OriginalName": "Run",
          "Parameters": [
            {
              "Name": "name",
              "IsNullChecked": true,
              "IsOptional": false,
              "IsRestArgs": false,
              "Description": "",
              "Type": "any"
            },
            {
              "Name": "context",
              "IsNullChecked": false,
              "IsOptional": false,
              "IsRestArgs": false,
              "Description": "",
              "Type": "any"
            }
          ],
          "Return": {
            "Type": "any",
            "Description": ""
          },
          "Description": ""
        },
        {
          "Name": "GetTarget",
          "Type": "function",
          "OriginalName": "GetTarget",
          "Parameters": [
            {
              "Name": "name",
              "IsNullChecked": true,
              "IsOptional": false,
              "IsRestArgs": false,
              "Description": "",
              "Type": "any"
            }
          ],
          "Return": {
            "Type": "any",
            "Description": ""
          },
          "Description": ""
        }
      ],
      "OriginalName": "BuildSystem",
      "Description": ""
    },
    {
      "SectionName": "BuildLogger",
      "SectionType": "class-definition",
      "Sections": [],
      "Properties": [
        {
          "Name": "Tag",
          "Type": "value",
          "Value": null
        },
        {
          "Name": "BuildLogger",
          "Type": "function",
          "OriginalName": "BuildLogger",
          "Parameters": [
            {
              "Name": "tag",
              "IsNullChecked": true,
              "IsOptional": false,
              "IsRestArgs": false,
              "Description": "The tag that is displayed",
              "Type": "string"
            }
          ],
          "Return": {
            "Type": "any",
            "Description": ""
          },
          "Description": "Creates a new BuildLogger instance with the specified tag"
        },
        {
          "Name": "Log",
          "Type": "function",
          "OriginalName": "Log",
          "Parameters": [
            {
              "Name": "msg",
              "IsNullChecked": true,
              "IsOptional": false,
              "IsRestArgs": false,
              "Description": "The message",
              "Type": "any"
            }
          ],
          "Return": {
            "Type": "void",
            "Description": ""
          },
          "Description": "Logs a message"
        },
        {
          "Name": "Warn",
          "Type": "function",
          "OriginalName": "Warn",
          "Parameters": [
            {
              "Name": "msg",
              "IsNullChecked": true,
              "IsOptional": false,
              "IsRestArgs": false,
              "Description": "The message",
              "Type": "any"
            }
          ],
          "Return": {
            "Type": "void",
            "Description": ""
          },
          "Description": "Logs a warning"
        },
        {
          "Name": "Error",
          "Type": "function",
          "OriginalName": "Error",
          "Parameters": [
            {
              "Name": "msg",
              "IsNullChecked": true,
              "IsOptional": false,
              "IsRestArgs": false,
              "Description": "The error",
              "Type": "any"
            }
          ],
          "Return": {
            "Type": "void",
            "Description": ""
          },
          "Description": "Logs an error"
        }
      ],
      "OriginalName": "BuildLogger",
      "Description": "Implements a Logger that will output logs prefixed with different tags."
    },
    {
      "SectionName": "BuildTarget",
      "SectionType": "class-definition",
      "Sections": [],
      "Properties": [
        {
          "Name": "Info",
          "Type": "value",
          "Value": null
        },
        {
          "Name": "Logger",
          "Type": "value",
          "Value": null
        },
        {
          "Name": "BuildTarget",
          "Type": "function",
          "OriginalName": "BuildTarget",
          "Parameters": [
            {
              "Name": "info",
              "IsNullChecked": true,
              "IsOptional": false,
              "IsRestArgs": false,
              "Description": "The build target info",
              "Type": "any"
            }
          ],
          "Return": {
            "Type": "any",
            "Description": ""
          },
          "Description": "Constructs a new Build Target from the specified build target info"
        },
        {
          "Name": "GetName",
          "Type": "function",
          "OriginalName": "GetName",
          "Parameters": [],
          "Return": {
            "Type": "string",
            "Description": "Build Target Name"
          },
          "Description": "Returns the Build Target Name"
        },
        {
          "Name": "GetDependencies",
          "Type": "function",
          "OriginalName": "GetDependencies",
          "Parameters": [],
          "Return": {
            "Type": "Array",
            "Description": "Build Target Dependencies"
          },
          "Description": "Returns the Build Target Dependencies"
        },
        {
          "Name": "GetScript",
          "Type": "function",
          "OriginalName": "GetScript",
          "Parameters": [],
          "Return": {
            "Type": "string",
            "Description": "Path to build target script. (null if not defined)"
          },
          "Description": "Returns the Build Target Script"
        },
        {
          "Name": "GetPreScript",
          "Type": "function",
          "OriginalName": "GetPreScript",
          "Parameters": [],
          "Return": {
            "Type": "string",
            "Description": "Path to build target PreScript. (null if not defined)"
          },
          "Description": "Returns the Build Target PreScript"
        },
        {
          "Name": "GetDescription",
          "Type": "function",
          "OriginalName": "GetDescription",
          "Parameters": [],
          "Return": {
            "Type": "string",
            "Description": "Build Target Description. (Name if not defined)"
          },
          "Description": "Returns the Build Target Description"
        },
        {
          "Name": "Save",
          "Type": "function",
          "OriginalName": "Save",
          "Parameters": [
            {
              "Name": "file",
              "IsNullChecked": true,
              "IsOptional": false,
              "IsRestArgs": false,
              "Description": "Path of the resulting build target file.",
              "Type": "string"
            }
          ],
          "Return": {
            "Type": "any",
            "Description": ""
          },
          "Description": "Saves the build target to a file"
        },
        {
          "Name": "ExecuteScript",
          "Type": "function",
          "OriginalName": "ExecuteScript",
          "Parameters": [
            {
              "Name": "scriptPath",
              "IsNullChecked": false,
              "IsOptional": false,
              "IsRestArgs": false,
              "Description": "the path to the script that will be executed.",
              "Type": "string"
            },
            {
              "Name": "context",
              "IsNullChecked": false,
              "IsOptional": false,
              "IsRestArgs": false,
              "Description": "the context that will be used to execute the script.",
              "Type": "any"
            }
          ],
          "Return": {
            "Type": "void",
            "Description": ""
          },
          "Description": "Executes a Script"
        },
        {
          "Name": "RunPreScript",
          "Type": "function",
          "OriginalName": "RunPreScript",
          "Parameters": [
            {
              "Name": "context",
              "IsNullChecked": false,
              "IsOptional": false,
              "IsRestArgs": false,
              "Description": "the context that will be used to execute the script.",
              "Type": "any"
            }
          ],
          "Return": {
            "Type": "void",
            "Description": ""
          },
          "Description": "Runs the Pre Script"
        },
        {
          "Name": "RunScript",
          "Type": "function",
          "OriginalName": "RunScript",
          "Parameters": [
            {
              "Name": "context",
              "IsNullChecked": false,
              "IsOptional": false,
              "IsRestArgs": false,
              "Description": "the context that will be used to execute the script.",
              "Type": "any"
            }
          ],
          "Return": {
            "Type": "void",
            "Description": ""
          },
          "Description": "Runs the Script"
        },
        {
          "Name": "Run",
          "Type": "function",
          "OriginalName": "Run",
          "Parameters": [
            {
              "Name": "system",
              "IsNullChecked": true,
              "IsOptional": false,
              "IsRestArgs": false,
              "Description": "the build system that this build target is running in.",
              "Type": "BuildSystem"
            },
            {
              "Name": "context",
              "IsNullChecked": false,
              "IsOptional": false,
              "IsRestArgs": false,
              "Description": "the context that will be used to execute the build target.",
              "Type": "any"
            }
          ],
          "Return": {
            "Type": "void",
            "Description": ""
          },
          "Description": "Runs the Build Target"
        }
      ],
      "OriginalName": "BuildTarget",
      "Description": "Models a Build Target in the Build System Pipeline"
    },
    {
      "SectionName": "BuildTargetDirectoryResolver",
      "SectionType": "class-definition",
      "Sections": [
        {
          "SectionName": "Targets",
          "SectionType": "namespace",
          "Sections": [],
          "Properties": []
        }
      ],
      "Properties": [
        {
          "Name": "Path",
          "Type": "value",
          "Value": null
        },
        {
          "Name": "BuildTargetDirectoryResolver",
          "Type": "function",
          "OriginalName": "BuildTargetDirectoryResolver",
          "Parameters": [
            {
              "Name": "path",
              "IsNullChecked": true,
              "IsOptional": false,
              "IsRestArgs": false,
              "Description": "The Path that contains the build target .json files",
              "Type": "string"
            },
            {
              "Name": "context",
              "IsNullChecked": false,
              "IsOptional": false,
              "IsRestArgs": false,
              "Description": "The contex the build targets are resolved with.",
              "Type": "any"
            }
          ],
          "Return": {
            "Type": "any",
            "Description": ""
          },
          "Description": "Creates a new instance of the build Target Resolver class"
        },
        {
          "Name": "LoadTargets",
          "Type": "function",
          "OriginalName": "LoadTargets",
          "Parameters": [
            {
              "Name": "context",
              "IsNullChecked": false,
              "IsOptional": false,
              "IsRestArgs": false,
              "Description": "the context which is used to resolve the build targets",
              "Type": "any"
            }
          ],
          "Return": {
            "Type": "void",
            "Description": ""
          },
          "Description": "Loads all targets from the Path that was specified in the constructor."
        },
        {
          "Name": "Resolve",
          "Type": "function",
          "OriginalName": "Resolve",
          "Parameters": [
            {
              "Name": "name",
              "IsNullChecked": true,
              "IsOptional": false,
              "IsRestArgs": false,
              "Description": "the build target name",
              "Type": "string"
            }
          ],
          "Return": {
            "Type": "any",
            "Description": "The Build Target with the specified name."
          },
          "Description": "Resolves a build target with the specified name. returns null if no target was found."
        }
      ],
      "OriginalName": "BuildTargetDirectoryResolver",
      "Description": "Resolves Build Target Directories"
    },
    {
      "SectionName": "BuildTargetLoader",
      "SectionType": "class-definition",
      "Sections": [],
      "Properties": [
        {
          "Name": "ResolveString",
          "Type": "function",
          "OriginalName": "ResolveString",
          "Parameters": [
            {
              "Name": "context",
              "IsNullChecked": true,
              "IsOptional": false,
              "IsRestArgs": false,
              "Description": "The Context that the string is resolved with",
              "Type": "Table"
            },
            {
              "Name": "str",
              "IsNullChecked": false,
              "IsOptional": false,
              "IsRestArgs": false,
              "Description": "The String to be resolved",
              "Type": "string"
            }
          ],
          "Return": {
            "Type": "string",
            "Description": "the resolved string"
          },
          "Description": "Resolves a String Value with the specified context."
        },
        {
          "Name": "ResolveTable",
          "Type": "function",
          "OriginalName": "ResolveTable",
          "Parameters": [
            {
              "Name": "context",
              "IsNullChecked": true,
              "IsOptional": false,
              "IsRestArgs": false,
              "Description": "The Context that the Table is resolved with",
              "Type": "Table"
            },
            {
              "Name": "table",
              "IsNullChecked": false,
              "IsOptional": false,
              "IsRestArgs": false,
              "Description": "The Table to be resolved",
              "Type": "Table"
            }
          ],
          "Return": {
            "Type": "Table",
            "Description": "the resolved string"
          },
          "Description": "Resolves a Table with the specified context."
        },
        {
          "Name": "ResolveArray",
          "Type": "function",
          "OriginalName": "ResolveArray",
          "Parameters": [
            {
              "Name": "context",
              "IsNullChecked": true,
              "IsOptional": false,
              "IsRestArgs": false,
              "Description": "The Context that the Array is resolved with",
              "Type": "Table"
            },
            {
              "Name": "array",
              "IsNullChecked": false,
              "IsOptional": false,
              "IsRestArgs": false,
              "Description": "The Array to be resolved",
              "Type": "Array"
            }
          ],
          "Return": {
            "Type": "Array",
            "Description": "the resolved Array"
          },
          "Description": "Resolves an Array with the specified context."
        },
        {
          "Name": "Resolve",
          "Type": "function",
          "OriginalName": "Resolve",
          "Parameters": [
            {
              "Name": "context",
              "IsNullChecked": true,
              "IsOptional": false,
              "IsRestArgs": false,
              "Description": "The Context that the Object is resolved with",
              "Type": "Table"
            },
            {
              "Name": "obj",
              "IsNullChecked": false,
              "IsOptional": false,
              "IsRestArgs": false,
              "Description": "The Object to be resolved",
              "Type": "any"
            }
          ],
          "Return": {
            "Type": "any",
            "Description": "the resolved Object"
          },
          "Description": "Resolves an Object with the specified context."
        },
        {
          "Name": "Load",
          "Type": "function",
          "OriginalName": "Load",
          "Parameters": [
            {
              "Name": "file",
              "IsNullChecked": true,
              "IsOptional": false,
              "IsRestArgs": false,
              "Description": "The Build Target File",
              "Type": "string"
            },
            {
              "Name": "context",
              "IsNullChecked": false,
              "IsOptional": false,
              "IsRestArgs": false,
              "Description": "The Context that the build target is resolved with",
              "Type": "Table"
            }
          ],
          "Return": {
            "Type": "any",
            "Description": "the resolved Object"
          },
          "Description": "Loads a build target from the specified file and resolves it with the supplied context."
        }
      ],
      "OriginalName": "BuildTargetLoader",
      "Description": "Loads Build Targets"
    },
    {
      "SectionName": "BuildTargetResolver",
      "SectionType": "class-definition",
      "Sections": [
        {
          "SectionName": "_Funcs",
          "SectionType": "namespace",
          "Sections": [],
          "Properties": []
        }
      ],
      "Properties": [
        {
          "Name": "AddResolverFunc",
          "Type": "function",
          "OriginalName": "AddResolverFunc",
          "Parameters": [
            {
              "Name": "func",
              "IsNullChecked": true,
              "IsOptional": false,
              "IsRestArgs": false,
              "Description": "Resolver Function",
              "Type": "Function"
            }
          ],
          "Return": {
            "Type": "void",
            "Description": ""
          },
          "Description": "Adds a Resolver Function"
        },
        {
          "Name": "Resolve",
          "Type": "function",
          "OriginalName": "Resolve",
          "Parameters": [
            {
              "Name": "name",
              "IsNullChecked": true,
              "IsOptional": false,
              "IsRestArgs": false,
              "Description": "Name of the Build Target",
              "Type": "string"
            }
          ],
          "Return": {
            "Type": "any",
            "Description": "The Build Target with the specified name"
          },
          "Description": "Resolves a Build Target by Name"
        }
      ],
      "OriginalName": "BuildTargetResolver",
      "Description": "Resolves Build Targets by Name"
    }
  ],
  "Properties": []
}